{
    "dimensions": [
        {
            "dim": 6,
            "override": false,
			"dimensiontype":
            {
                "id": 6,
                "name": "Nether Mining Dimension",
                "suffix": "_dim6",
                "keeploaded": false,
                "worldprovider": "WorldProviderHellJED"
            }
        },
		{
            "dim": 8,
            "override": false,
			"dimensiontype":
            {
                "id": 8,
                "name": "Spawn Platform Dimension",
                "suffix": "_dim8",
                "keeploaded": false,
                "worldprovider": "WorldProviderSurfaceJED"
            },
			"worldinfo_onetime": {
                "generatorName": "flat",
                "generatorOptions": "3;minecraft:air;127;",
                "DayTime": 6000,
                "GameRules": {
                    "doMobSpawning": "false"
                }
            },
            "jed": {
                "CanSpawnHostiles": false,
                "CanSpawnPeacefulMobs": false
            }
        },
        {
            "dim": 1,
			"worldinfo": {
				"BorderCenterX": 0,
				"BorderCenterZ": 0,
				"BorderSize": 320000
            }
        }
    ]
}